snaketrail/__init__.py
snaketrail/cli.py
snaketrail/core.py
snaketrail-0.1.0.dist-info/METADATA
snaketrail-0.1.0.dist-info/WHEEL
snaketrail-0.1.0.dist-info/entry_points.txt
snaketrail-0.1.0.dist-info/RECORD
