Metadata-Version: 2.4
Name: snaketrail
Version: 0.1.0
Summary: Trace the snake: list transitive local imports and unused Python files.
Author-email: Jacques Fleischer <j.fleischer@ufl.edu>
License: MIT
Keywords: dependency-graph,imports,python,static-analysis
Classifier: License :: OSI Approved :: MIT License
Classifier: Operating System :: OS Independent
Classifier: Programming Language :: Python :: 3
Classifier: Programming Language :: Python :: 3 :: Only
Classifier: Topic :: Software Development :: Build Tools
Classifier: Topic :: Software Development :: Code Generators
Classifier: Topic :: Software Development :: Quality Assurance
Requires-Python: >=3.8
